MLAC/Neural_networks.py
MLAC/__init__.py
MLAC/crack_detection_algorithms.py
MLAC/test.py
MLAC-0.2.dist-info/LICENSE.txt
MLAC-0.2.dist-info/METADATA
MLAC-0.2.dist-info/WHEEL
MLAC-0.2.dist-info/top_level.txt
MLAC-0.2.dist-info/RECORD
