Metadata-Version: 2.1
Name: MLAC
Version: 0.2
Summary: Code for comparing different machine learning algorithms for binary classification.
Home-page: https://github.com/Joel-H-dot/MLAC
Author: Joel Hampton
Author-email: joelelihampton@outlook.com
License: MIT
Keywords: Machine Learning,Binary Classification,SciKit-learn,neural networks
Platform: UNKNOWN
Classifier: Development Status :: 4 - Beta
Classifier: Intended Audience :: Science/Research 
Classifier: License :: OSI Approved :: MIT License
Classifier: Programming Language :: Python :: 3
License-File: LICENSE.txt
Requires-Dist: numpy
Requires-Dist: sklearn
Requires-Dist: scipy
Requires-Dist: openpyxl
Requires-Dist: tensorflow
Requires-Dist: keras-tuner
Requires-Dist: scikit-learn
Requires-Dist: pandas
